pysisu/__init__.py
pysisu/example_usage.py
pysisu/formats.py
pysisu/latest_analysis_result.py
pysisu/pysisu_class.py
pysisu/query_helpers.py
pysisu/version.py
pysisu/proto/__init__.py
pysisu/proto/google/__init__.py
pysisu/proto/google/api/__init__.py
pysisu/proto/grpc/__init__.py
pysisu/proto/grpc/gateway/__init__.py
pysisu/proto/grpc/gateway/protoc_gen_openapiv2/__init__.py
pysisu/proto/grpc/gateway/protoc_gen_openapiv2/options/__init__.py
pysisu/proto/sisu/__init__.py
pysisu/proto/sisu/v1/__init__.py
pysisu/proto/sisu/v1/api/__init__.py
pysisu/scripts/__init__.py
pysisu/scripts/ensure_version_bumped.py
pysisu/tests/__init__.py
pysisu/tests/conftest.py
pysisu/tests/helpers_for_tests.py
pysisu/tests/test_analysis_results_output.py
pysisu/tests/test_analysis_results_proto.py
pysisu/tests/test_endpoints.py
pysisu/tests/test_pagination.py
pysisu/tests/test_version_control.py
pysisu-0.4.20.dist-info/LICENSE
pysisu-0.4.20.dist-info/METADATA
pysisu-0.4.20.dist-info/WHEEL
pysisu-0.4.20.dist-info/top_level.txt
pysisu-0.4.20.dist-info/RECORD
