Metadata-Version: 2.1
Name: pysisu
Version: 0.4.20
Home-page: https://github.com/sisudata/pysisu
Author: Sisu Data
License: Apache
License-File: LICENSE
Requires-Dist: betterproto >=2.0.0b4
Requires-Dist: requests-cache
Requires-Dist: requests
